Workbook

Sheet Presupuesto
A1: Presupuesto: balanza comercial con impresora de tickets
A2: Una unidad completa. Precios en pesos argentinos relevados el 7 y 8 de octubre de 2026. Envíos y mano de obra no incluidos.
A4: Ítem | B4: Descripción | C4: Cant. | D4: Precio unitario | E4: Subtotal | F4: Nota
A5: 1. Balanza base
A6: Balanza comercial digital 40 kg | B6: Estructura, celda de carga, displays, teclado y batería | C6: 1 | D6: 35000 | E6: =C6*D6 -> 35000 | F6: Poné 0 si usás una balanza que ya tenés.
A7: Subtotal balanza base | E7: =SUM(E6:E6) -> 35000
A9: 2. Electrónica de control
A10: Placa ESP32-S3 DevKitC-1 compatible | B10: Controla la balanza, guarda los productos y maneja la impresora por USB | C10: 1 | D10: 18879 | E10: =C10*D10 -> 18879 | F10: Antena WiFi incorporada.
A11: Módulo HX711 | B11: Lee la celda de carga | C11: 1 | D11: 3290 | E11: =C11*D11 -> 3290
A12: Fuente 9 V 2 A | B12: Alimentación de la electrónica | C12: 1 | D12: 11950 | E12: =C12*D12 -> 11950
A13: Regulador step-down LM2596 | B13: Baja a 5 V para la placa y el conector USB | C13: 1 | D13: 4682 | E13: =C13*D13 -> 4682
A14: Jack DC hembra con bornera | B14: Entrada de la fuente | C14: 1 | D14: 600 | E14: =C14*D14 -> 600
A15: Conector USB-A hembra de panel | B15: Para enchufar y desenchufar la impresora | C15: 1 | D15: 5000 | E15: =C15*D15 -> 5000
A16: Varios de armado | B16: Capacitores, cables, termocontraíble, tornillos | C16: 1 | D16: 3000 | E16: =C16*D16 -> 3000 | F16: Monto estimado, no relevado en una tienda.
A17: Subtotal electrónica de control | E17: =SUM(E10:E16) -> 47401
A19: 3. Impresora y papel
A20: Impresora térmica Xprinter XP-58IIH USB | B20: Tickets de 58 mm; trae fuente, cable USB y 5 rollos | C20: 1 | D20: 54399 | E20: =C20*D20 -> 54399 | F20: Precio de referencia.
A21: Rollos térmicos 57 mm x 30 m, pack x10 | B21: Reserva de papel | C21: 1 | D21: 6300 | E21: =C21*D21 -> 6300
A22: Subtotal impresora y papel | E22: =SUM(E20:E21) -> 60699
A24: 4. Desarrollo y pruebas (una sola vez)
A25: Kit 120 cables dupont | B25: Armado de pruebas en la mesa | C25: 1 | D25: 9809 | E25: =C25*D25 -> 9809
A26: Adaptador OTG USB-C a USB-A hembra | B26: Probar la impresora antes del armado final | C26: 1 | D26: 2638 | E26: =C26*D26 -> 2638
A27: Placa ESP32-S3 de repuesto | B27: Probar sin arriesgar la placa de la balanza | C27: 1 | D27: 18879 | E27: =C27*D27 -> 18879 | F27: Opcional.
A28: Subtotal desarrollo y pruebas (una sola vez) | E28: =SUM(E25:E27) -> 31326
A30: Resumen
A31: Costo de la balanza con impresora (secciones 1 a 3) | E31: =E7+E17+E22 -> 143100
A32: Desarrollo y pruebas (sección 4, una sola vez) | E32: =E28 -> 31326
A33: Subtotal | E33: =E31+E32 -> 174426
A34: Margen para imprevistos, envíos y aumentos | D34: 0.15 | E34: =E33*D34 -> 26163.9
A35: TOTAL A PEDIR | E35: =E33+E34 -> 200589.9
A37: Cada balanza adicional, con el mismo margen | E37: =E31*(1+D34) -> 164565 | F37: No repite los gastos de desarrollo.
A39: Amarillo: cantidades y margen editables. Azul: precios relevados en tiendas (ver hoja Fuentes). Negro: cálculos.

Sheet Fuentes
A1: Ítem | B1: Tienda | C1: Link | D1: Precio relevado
A2: Balanza comercial digital 40 kg | B2: Tecnoimpor | C2: https://www.tecnoimpor.com.ar/productos/balanza-digital-comercial-40-kg-con-calculo-de-precio-s-mastil-s/ | D2: =Presupuesto!D6 -> 35000
A3: Placa ESP32-S3 DevKitC-1 compatible | B3: Starware | C3: https://tienda.starware.com.ar/producto/placa-desarrollo-diy-espressif-compatible-esp32-s3-devkitc-1-n16r8-esp32-s3-wroom-1-8mb/ | D3: =Presupuesto!D10 -> 18879
A4: Módulo HX711 | B4: TodoMicro | C4: https://www.todomicro.com.ar/investigacion-desarrollo-y-prototipado/759-modulo-amplificador-hx711-para-celda-de-carga.html | D4: =Presupuesto!D11 -> 3290
A5: Fuente 9 V 2 A | B5: Nerdstore | C5: https://nerdstore.com.ar/producto/fuente-performance-9v-2a-plug-5-52-110mm/ | D5: =Presupuesto!D12 -> 11950
A6: Regulador step-down LM2596 | B6: TodoMicro | C6: https://www.todomicro.com.ar/step-down/589-modulo-lm2596-step-down-corriente-ajustable.html | D6: =Presupuesto!D13 -> 4682
A7: Jack DC hembra con bornera | B7: LED Universe | C7: https://www.leduniverse.com.ar/productos/ficha-plug-jack-hembra-5-5-x-2-1mm-bornera/ | D7: =Presupuesto!D14 -> 600
A8: Conector USB-A hembra de panel | B8: West Solution | C8: https://westsolution.com.ar/productos/conector-usb-tipo-a-hembra-a-chasis-pc-board-montaje-frontal/ | D8: =Presupuesto!D15 -> 5000
A9: Varios de armado | B9: Estimado | C9: Sin fuente: monto estimado | D9: =Presupuesto!D16 -> 3000
A10: Impresora térmica Xprinter XP-58IIH USB | B10: Mercado Libre (vía MejoresCompras) | C10: https://mejorescompras.com.ar/precio/MLA36701582--impresora-termica-xprinter-xp58iih-bluetooth-58mm-comandera-pos-tickets-alta-velocidad-negro | D10: =Presupuesto!D20 -> 54399
A11: Rollos térmicos 57 mm x 30 m, pack x10 | B11: Inkgenio | C11: https://inkgenio.com.ar/Rollos-Rollos-Termicos/3910-rollo-termico-57x30-pack-x10-7798070391182.html | D11: =Presupuesto!D21 -> 6300
A12: Kit 120 cables dupont | B12: TodoMicro | C12: https://www.todomicro.com.ar/628-kit-120-cables-20cm-protoboard-compatible-con-arduino.html | D12: =Presupuesto!D25 -> 9809
A13: Adaptador OTG USB-C a USB-A hembra | B13: TodoMicro | C13: https://www.todomicro.com.ar/567-adaptador-usb-c-a-usb30.html | D13: =Presupuesto!D26 -> 2638
A14: Placa ESP32-S3 de repuesto | B14: Starware | C14: https://tienda.starware.com.ar/producto/placa-desarrollo-diy-espressif-compatible-esp32-s3-devkitc-1-n16r8-esp32-s3-wroom-1-8mb/ | D14: =Presupuesto!D27 -> 18879
